{
  "new_items": [
    {
      "repo": "SecureBananaLabs/bug-bounty",
      "number": 11000,
      "title": "User creation should validate payloads and block admin role self-assignment",
      "url": "https://github.com/SecureBananaLabs/bug-bounty/issues/11000",
      "recommendation": "pursue",
      "total_score": 102
    },
    {
      "repo": "pancakeswap/pancake-v3-contracts",
      "number": 32,
      "title": "Bug Bounty",
      "url": "https://github.com/pancakeswap/pancake-v3-contracts/issues/32",
      "recommendation": "pursue",
      "total_score": 95
    },
    {
      "repo": "tenstorrent/tt-metal",
      "number": 49307,
      "title": "[Bounty] Command-R bringup using TTNN APIs",
      "url": "https://github.com/tenstorrent/tt-metal/issues/49307",
      "recommendation": "skip",
      "total_score": 63
    }
  ],
  "dropped_items": [],
  "recommendation_changes": [],
  "score_changes": []
}