{
  "generated_at_utc": "2026-06-27T14:56:27Z",
  "history_window_runs": 12,
  "history_min_skip_runs": 4,
  "history_min_unique_issues": 2,
  "blocked_repos": [
    "archestra-ai/archestra"
  ],
  "repo_stats": {
    "SecureBananaLabs/bug-bounty": {
      "total_seen": 2,
      "skip_count": 0,
      "review_count": 0,
      "pursue_count": 2,
      "unique_issues": [
        8831,
        8832
      ]
    },
    "tenstorrent/tt-metal": {
      "total_seen": 3,
      "skip_count": 2,
      "review_count": 0,
      "pursue_count": 1,
      "unique_issues": [
        48285,
        48287,
        48311
      ]
    },
    "projectdiscovery/nuclei": {
      "total_seen": 2,
      "skip_count": 2,
      "review_count": 0,
      "pursue_count": 0,
      "unique_issues": [
        6532,
        6674
      ]
    },
    "archestra-ai/archestra": {
      "total_seen": 5,
      "skip_count": 5,
      "review_count": 0,
      "pursue_count": 0,
      "unique_issues": [
        3218,
        3855,
        4468,
        4998,
        5033
      ]
    },
    "Dokploy/templates": {
      "total_seen": 1,
      "skip_count": 1,
      "review_count": 0,
      "pursue_count": 0,
      "unique_issues": [
        152
      ]
    },
    "openmetaearth/me-hub": {
      "total_seen": 1,
      "skip_count": 0,
      "review_count": 1,
      "pursue_count": 0,
      "unique_issues": [
        1411
      ]
    },
    "tailcallhq/tailcallhq.github.io": {
      "total_seen": 1,
      "skip_count": 1,
      "review_count": 0,
      "pursue_count": 0,
      "unique_issues": [
        373
      ]
    },
    "antinomyhq/forge": {
      "total_seen": 1,
      "skip_count": 1,
      "review_count": 0,
      "pursue_count": 0,
      "unique_issues": [
        389
      ]
    },
    "Dokploy/dokploy": {
      "total_seen": 2,
      "skip_count": 2,
      "review_count": 0,
      "pursue_count": 0,
      "unique_issues": [
        416,
        1413
      ]
    },
    "revertinc/revert": {
      "total_seen": 2,
      "skip_count": 2,
      "review_count": 0,
      "pursue_count": 0,
      "unique_issues": [
        372,
        551
      ]
    },
    "tscircuit/dsn-converter": {
      "total_seen": 1,
      "skip_count": 1,
      "review_count": 0,
      "pursue_count": 0,
      "unique_issues": [
        54
      ]
    },
    "tailcallhq/graphql-conf-2024": {
      "total_seen": 1,
      "skip_count": 1,
      "review_count": 0,
      "pursue_count": 0,
      "unique_issues": [
        1
      ]
    },
    "tailcallhq/rust-grpc": {
      "total_seen": 1,
      "skip_count": 1,
      "review_count": 0,
      "pursue_count": 0,
      "unique_issues": [
        44
      ]
    },
    "tscircuit/jlcsearch": {
      "total_seen": 1,
      "skip_count": 1,
      "review_count": 0,
      "pursue_count": 0,
      "unique_issues": [
        92
      ]
    }
  },
  "top_repeat_skips": [
    {
      "repo": "archestra-ai/archestra",
      "total_seen": 5,
      "skip_count": 5,
      "review_count": 0,
      "pursue_count": 0,
      "unique_issues": [
        3218,
        3855,
        4468,
        4998,
        5033
      ]
    },
    {
      "repo": "tenstorrent/tt-metal",
      "total_seen": 3,
      "skip_count": 2,
      "review_count": 0,
      "pursue_count": 1,
      "unique_issues": [
        48285,
        48287,
        48311
      ]
    },
    {
      "repo": "revertinc/revert",
      "total_seen": 2,
      "skip_count": 2,
      "review_count": 0,
      "pursue_count": 0,
      "unique_issues": [
        372,
        551
      ]
    },
    {
      "repo": "projectdiscovery/nuclei",
      "total_seen": 2,
      "skip_count": 2,
      "review_count": 0,
      "pursue_count": 0,
      "unique_issues": [
        6532,
        6674
      ]
    },
    {
      "repo": "Dokploy/dokploy",
      "total_seen": 2,
      "skip_count": 2,
      "review_count": 0,
      "pursue_count": 0,
      "unique_issues": [
        416,
        1413
      ]
    },
    {
      "repo": "tscircuit/jlcsearch",
      "total_seen": 1,
      "skip_count": 1,
      "review_count": 0,
      "pursue_count": 0,
      "unique_issues": [
        92
      ]
    },
    {
      "repo": "tscircuit/dsn-converter",
      "total_seen": 1,
      "skip_count": 1,
      "review_count": 0,
      "pursue_count": 0,
      "unique_issues": [
        54
      ]
    },
    {
      "repo": "tailcallhq/tailcallhq.github.io",
      "total_seen": 1,
      "skip_count": 1,
      "review_count": 0,
      "pursue_count": 0,
      "unique_issues": [
        373
      ]
    },
    {
      "repo": "tailcallhq/rust-grpc",
      "total_seen": 1,
      "skip_count": 1,
      "review_count": 0,
      "pursue_count": 0,
      "unique_issues": [
        44
      ]
    },
    {
      "repo": "tailcallhq/graphql-conf-2024",
      "total_seen": 1,
      "skip_count": 1,
      "review_count": 0,
      "pursue_count": 0,
      "unique_issues": [
        1
      ]
    },
    {
      "repo": "antinomyhq/forge",
      "total_seen": 1,
      "skip_count": 1,
      "review_count": 0,
      "pursue_count": 0,
      "unique_issues": [
        389
      ]
    },
    {
      "repo": "Dokploy/templates",
      "total_seen": 1,
      "skip_count": 1,
      "review_count": 0,
      "pursue_count": 0,
      "unique_issues": [
        152
      ]
    },
    {
      "repo": "SecureBananaLabs/bug-bounty",
      "total_seen": 2,
      "skip_count": 0,
      "review_count": 0,
      "pursue_count": 2,
      "unique_issues": [
        8831,
        8832
      ]
    },
    {
      "repo": "openmetaearth/me-hub",
      "total_seen": 1,
      "skip_count": 0,
      "review_count": 1,
      "pursue_count": 0,
      "unique_issues": [
        1411
      ]
    }
  ]
}